dist_prb_a/Binomialdistribution.py
dist_prb_a/Gaussiandistribution.py
dist_prb_a/Generaldistribution.py
dist_prb_a/__init__.py
dist_prb_a-1.2.dist-info/DESCRIPTION.rst
dist_prb_a-1.2.dist-info/METADATA
dist_prb_a-1.2.dist-info/RECORD
dist_prb_a-1.2.dist-info/WHEEL
dist_prb_a-1.2.dist-info/metadata.json
dist_prb_a-1.2.dist-info/top_level.txt
