Metadata-Version: 2.0
Name: dist-prb-a
Version: 1.2
Summary: Gaussian and Binomial distributions
Home-page: UNKNOWN
Author: S.Radu
Author-email: myaddress@email.org
License: MIT
Platform: UNKNOWN
Classifier: Development Status :: 3 - Alpha
Classifier: Intended Audience :: Developers
Classifier: Topic :: Software Development :: Build Tools
Classifier: License :: OSI Approved :: MIT License
Classifier: Programming Language :: Python :: 3
Classifier: Programming Language :: Python :: 3.4
Classifier: Programming Language :: Python :: 3.5
Classifier: Programming Language :: Python :: 3.6
